notification_center/__init__.py
notification_center/frontend/.gitignore
notification_center/frontend/.prettierrc
notification_center/frontend/package-lock.json
notification_center/frontend/package.json
notification_center/frontend/tsconfig.json
notification_center/frontend/build/asset-manifest.json
notification_center/frontend/build/bootstrap.min.css
notification_center/frontend/build/index.html
notification_center/frontend/build/sample.html
notification_center/frontend/build/static/js/main.87ff2e29.js
notification_center/frontend/build/static/js/main.87ff2e29.js.LICENSE.txt
notification_center/frontend/build/static/js/main.87ff2e29.js.map
notification_center/frontend/public/bootstrap.min.css
notification_center/frontend/public/index.html
notification_center/frontend/public/sample.html
notification_center/frontend/src/NotificationCenter.tsx
notification_center/frontend/src/index.tsx
notification_center/frontend/src/react-app-env.d.ts
streamlit_notification_center_component-0.0.13.dist-info/LICENSE
streamlit_notification_center_component-0.0.13.dist-info/METADATA
streamlit_notification_center_component-0.0.13.dist-info/WHEEL
streamlit_notification_center_component-0.0.13.dist-info/top_level.txt
streamlit_notification_center_component-0.0.13.dist-info/RECORD
