Metadata-Version: 2.1
Name: streamlit-notification-center-component
Version: 0.0.13
Summary: Streamlit component that listens for postMessage events and reports back
Home-page: 
Author: Brielle Harrison
Author-email: bharrison@raptive.com
Requires-Python: >=3.7
License-File: LICENSE
Requires-Dist: streamlit (>=0.63)
Requires-Dist: beautifulsoup4
Requires-Dist: lxml
